ddpc/__init__.py
ddpc/__main__.py
ddpc/_cli_base.py
ddpc/_utils.py
ddpc/cli.py
ddpc/data/__init__.py
ddpc/data/__main__.py
ddpc/data/_cli_base.py
ddpc/data/band.py
ddpc/data/cli.py
ddpc/data/dos.py
ddpc/data/export.py
ddpc/data/processors.py
ddpc/data/utils.py
ddpc/structure/__init__.py
ddpc/structure/__main__.py
ddpc/structure/_cli_base.py
ddpc/structure/cli.py
ddpc/structure/io.py
ddpc/structure/orthogonal.py
ddpc/structure/primitive.py
ddpc/structure/readers/__init__.py
ddpc/structure/readers/dspaw_as.py
ddpc/structure/readers/rescu_xyz.py
ddpc/structure/symmetry.py
ddpc/structure/transform.py
ddpc/structure/writers/__init__.py
ddpc/structure/writers/dspaw_as.py
ddpc/structure/writers/rescu_xyz.py
ddpc-2025.12.9.dist-info/WHEEL
ddpc-2025.12.9.dist-info/entry_points.txt
ddpc-2025.12.9.dist-info/METADATA
ddpc-2025.12.9.dist-info/RECORD
