Metadata-Version: 2.3
Name: ddpc
Version: 2025.12.9
Summary: Dft Data Processing Core
Author: xbugs221
License: MIT
Classifier: Development Status :: 4 - Beta
Classifier: Intended Audience :: Science/Research
Classifier: License :: OSI Approved :: MIT License
Classifier: Programming Language :: Python :: 3
Classifier: Programming Language :: Python :: 3.12
Classifier: Programming Language :: Python :: 3.13
Classifier: Programming Language :: Python :: 3.14
Classifier: Topic :: Scientific/Engineering :: Chemistry
Classifier: Topic :: Scientific/Engineering :: Physics
Requires-Dist: click>=8.1
Requires-Dist: rich>=13.0
Requires-Dist: ddpc[data] ; extra == 'basic'
Requires-Dist: ddpc[structure] ; extra == 'basic'
Requires-Dist: numpy ; extra == 'data'
Requires-Dist: ddpc[data] ; extra == 'data-full'
Requires-Dist: h5py<3.14 ; python_full_version < '3.14' and extra == 'data-full'
Requires-Dist: h5py>=3.14 ; python_full_version >= '3.14' and extra == 'data-full'
Requires-Dist: ddpc[data-full] ; extra == 'full'
Requires-Dist: ddpc[structure-full] ; extra == 'full'
Requires-Dist: ase>=3.25 ; extra == 'structure'
Requires-Dist: ddpc[structure] ; extra == 'structure-full'
Requires-Dist: spglib>=2.6 ; extra == 'structure-full'
Requires-Python: >=3.12
Provides-Extra: basic
Provides-Extra: data
Provides-Extra: data-full
Provides-Extra: full
Provides-Extra: structure
Provides-Extra: structure-full
